[
  {"type":"directory","name":"./instance/gallery.pak","size":4096,"contents":[
    {"type":"file","name":"thumb_christmas2017.dat","size":262272},
    {"type":"file","name":"thumb_christmas2018.dat","size":262272},
    {"type":"file","name":"thumb_ellielulu.dat","size":262272},
    {"type":"file","name":"thumb_frb2019.dat","size":262272},
    {"type":"file","name":"thumb_halloween2018.dat","size":262272},
    {"type":"file","name":"thumb_halloween2019.dat","size":262272},
    {"type":"file","name":"thumb_halloween2021.dat","size":262272},
    {"type":"file","name":"thumb_kai.dat","size":262272},
    {"type":"file","name":"thumb_marc.dat","size":262272},
    {"type":"file","name":"thumb_mioevent.dat","size":262272},
    {"type":"file","name":"thumb_miuceore.dat","size":262272},
    {"type":"file","name":"thumb_newboxart.dat","size":262272},
    {"type":"file","name":"thumb_nicoarthur.dat","size":262272},
    {"type":"file","name":"thumb_oldguardians.dat","size":262272},
    {"type":"file","name":"thumb_originalboxart.dat","size":262272},
    {"type":"file","name":"thumb_qp.dat","size":262272},
    {"type":"file","name":"thumb_school.dat","size":262272},
    {"type":"file","name":"thumb_shroom.dat","size":262272},
    {"type":"file","name":"thumb_spring2019.dat","size":262272},
    {"type":"file","name":"thumb_spring2020.dat","size":262272},
    {"type":"file","name":"thumb_starbreaker.dat","size":262272},
    {"type":"file","name":"thumb_suguri.dat","size":262272},
    {"type":"file","name":"thumb_summer2018.dat","size":262272},
    {"type":"file","name":"thumb_summer2019.dat","size":262272},
    {"type":"file","name":"thumb_summer2020.dat","size":262272},
    {"type":"file","name":"thumb_summer2021.dat","size":262272},
    {"type":"file","name":"thumb_summer2022.dat","size":262272},
    {"type":"file","name":"thumb_sweetbreaker.dat","size":262272},
    {"type":"file","name":"thumb_valentines2018.dat","size":262272},
    {"type":"file","name":"thumb_winter2020.dat","size":262272},
    {"type":"file","name":"thumb_winter2022_2.dat","size":262272},
    {"type":"file","name":"thumb_winter2022contest_coolness1.dat","size":262272},
    {"type":"file","name":"thumb_winter2022contest_coolness2.dat","size":262272},
    {"type":"file","name":"thumb_winter2022contest_coolness3.dat","size":262272},
    {"type":"file","name":"thumb_winter2022contest_essence1.dat","size":262272},
    {"type":"file","name":"thumb_winter2022contest_essence2.dat","size":262272},
    {"type":"file","name":"thumb_winter2022contest_essence3.dat","size":262272},
    {"type":"file","name":"thumb_winter2022contest_essence4.dat","size":262272},
    {"type":"file","name":"thumb_winter2022contest_wholesome1.dat","size":262272},
    {"type":"file","name":"thumb_winter2022contest_wholesome2.dat","size":262272},
    {"type":"file","name":"thumb_winter2022contest_wholesome3.dat","size":262272}
  ]}
,
  {"type":"report","directories":1,"files":41}
]
