[
  {"type":"directory","name":"unzip/hyper.pak","size":4096,"contents":[
    {"type":"directory","name":"darkl","size":4096,"contents":[
      {"type":"file","name":"gen_glow.dat","size":262272,"md5":"df0b67f4f06a4b0910f456ce86cf4fa5"},
      {"type":"file","name":"gen_glowg.dat","size":262272,"md5":"5359a9b41bb359587ea944c142f9a5ca"},
      {"type":"file","name":"gen_glowr.dat","size":262272,"md5":"0fc7857d7a2864294c5b1b3bc02c9f92"},
      {"type":"file","name":"luckyegg_0.dat","size":65664,"md5":"e8ac1b9f30d272850716caad82a32949"},
      {"type":"file","name":"luckyegg_1.dat","size":65664,"md5":"2e00cb5357772a68465c1e11aada99bf"},
      {"type":"file","name":"luckyegg_2.dat","size":65664,"md5":"469c9a5d9b0463519c0a77c680f10c0f"},
      {"type":"file","name":"luckyegg_3.dat","size":65664,"md5":"c3bb76fd803fdad57905140cbe058e7c"},
      {"type":"file","name":"luckyegg_4.dat","size":65664,"md5":"d5ee2f1aad5532000b8d09d8f3a97822"},
      {"type":"file","name":"luckylunch.dat","size":65664,"md5":"c3bb76fd803fdad57905140cbe058e7c"},
      {"type":"file","name":"star00.dat","size":65664,"md5":"88e85949cbf97d30acfddab81988bd3b"},
      {"type":"file","name":"unluckyegg_0.dat","size":65664,"md5":"7484db538e29b5eefac734289cbde493"},
      {"type":"file","name":"unluckyegg_1.dat","size":65664,"md5":"88a1d3d3a89d63ff0b70b82d1dc841c9"},
      {"type":"file","name":"unluckyegg_2.dat","size":65664,"md5":"9f995ae9a8df8964f9c5e62e6056c30b"},
      {"type":"file","name":"unluckyegg_3.dat","size":65664,"md5":"d17806af33ec7101ff9b68f0d4c33638"},
      {"type":"file","name":"unluckyegg_4.dat","size":65664,"md5":"d5ee2f1aad5532000b8d09d8f3a97822"}
    ]},
    {"type":"directory","name":"krilapajamas","size":4096,"contents":[
      {"type":"file","name":"doll.dat","size":65664,"md5":"bd55045cf6a4288b234f2069d920f1cc"}
    ]},
    {"type":"directory","name":"mimyuujailbird","size":4096,"contents":[
      {"type":"file","name":"mjface.dat","size":131200,"md5":"880e131143ad0a1a2c4ca7566f198b8d"}
    ]},
    {"type":"directory","name":"motherpoppo","size":4096,"contents":[
      {"type":"file","name":"eff_motherpower.dat","size":262272,"md5":"7de9fcc92049d68a68a3a8d52dc6fdad"}
    ]},
    {"type":"directory","name":"sweetblogger","size":4096,"contents":[
      {"type":"file","name":"background.dat","size":2097280,"md5":"7e692c5a1d19c2c1cb62c04c35672ce3"},
      {"type":"file","name":"bubble.dat","size":65664,"md5":"5c5241f1c23be20b6887b2167bcbda80"},
      {"type":"file","name":"cloud.dat","size":262272,"md5":"fa2c81ef1ee84ca4364d28efe8ebdd47"},
      {"type":"file","name":"mountain.dat","size":1048704,"md5":"e9e1cc6cfb011eabd5616595659b550f"},
      {"type":"file","name":"platter.dat","size":262272,"md5":"4118ee4c06d40fbdb05841adfceb7b7a"},
      {"type":"file","name":"sweet01.dat","size":65664,"md5":"894ab97d431836a321e8bc95bce27519"},
      {"type":"file","name":"sweet02.dat","size":65664,"md5":"e24a87e1286fa803910ab8a661f7c5f4"},
      {"type":"file","name":"sweet03.dat","size":65664,"md5":"e2b78315c1e213e7117b51d4fa5ced88"},
      {"type":"file","name":"sweet04.dat","size":65664,"md5":"649c5d8c1db9a224d4ba679d89f78b4c"},
      {"type":"file","name":"sweet05.dat","size":65664,"md5":"746deb78343d6db7a1aa072cd1d21e37"},
      {"type":"file","name":"sweet06.dat","size":65664,"md5":"a86e2eb7a7b0fd2baed2b1ba3226aae4"}
    ]},
    {"type":"directory","name":"sweetcreator","size":4096,"contents":[
      {"type":"file","name":"butterflies.dat","size":1048704,"md5":"e3cfe9d6f324c68ccdfa0190d5366d43"},
      {"type":"file","name":"sweetcreatorbutterfly_front.dat","size":4194432,"md5":"71bdb6e9801ba5249e0c39e97b4c0639"},
      {"type":"file","name":"trail.dat","size":524416,"md5":"b94598ed2f5f7810ba27e257cf49de79"}
    ]},
    {"type":"directory","name":"sweetmaker","size":4096,"contents":[
      {"type":"file","name":"card.dat","size":65664,"md5":"0195c398ed6037d9d6ec6764ee72d4b7"},
      {"type":"file","name":"sweet01.dat","size":65664,"md5":"894ab97d431836a321e8bc95bce27519"},
      {"type":"file","name":"sweet02.dat","size":65664,"md5":"e24a87e1286fa803910ab8a661f7c5f4"},
      {"type":"file","name":"sweet03.dat","size":65664,"md5":"e2b78315c1e213e7117b51d4fa5ced88"},
      {"type":"file","name":"sweet04.dat","size":65664,"md5":"649c5d8c1db9a224d4ba679d89f78b4c"},
      {"type":"file","name":"sweet05.dat","size":65664,"md5":"746deb78343d6db7a1aa072cd1d21e37"},
      {"type":"file","name":"sweet06.dat","size":65664,"md5":"a86e2eb7a7b0fd2baed2b1ba3226aae4"}
    ]}
  ]}
,
  {"type":"report","directories":8,"files":39}
]
