[
  {"type":"directory","name":"./instance/voice_sys_peat.pak","size":4096,"contents":[
    {"type":"file","name":"1.WAV","size":25556},
    {"type":"file","name":"2.WAV","size":32678},
    {"type":"file","name":"3.WAV","size":45180},
    {"type":"file","name":"4.WAV","size":30316},
    {"type":"file","name":"5.WAV","size":36894},
    {"type":"file","name":"6.WAV","size":47166},
    {"type":"file","name":"BATTLE.WAV","size":38850},
    {"type":"file","name":"BONUS.WAV","size":65432},
    {"type":"file","name":"CHECK.WAV","size":76760},
    {"type":"file","name":"CONNECTED.WAV","size":62640},
    {"type":"file","name":"CONNECTFAILED.WAV","size":47912},
    {"type":"file","name":"CONNECTING.WAV","size":73354},
    {"type":"file","name":"DRAW.WAV","size":72136},
    {"type":"file","name":"DROP.WAV","size":66046},
    {"type":"file","name":"FRUITBATFACTORY.WAV","size":136836},
    {"type":"file","name":"KO.WAV","size":74022},
    {"type":"file","name":"LOBBYFULL.WAV","size":89348},
    {"type":"file","name":"MOVE.WAV","size":45780},
    {"type":"file","name":"NEWITEM.WAV","size":40214},
    {"type":"file","name":"NORMA1.WAV","size":159418},
    {"type":"file","name":"NORMA2.WAV","size":166480},
    {"type":"file","name":"NORMA3.WAV","size":170312},
    {"type":"file","name":"NORMA4.WAV","size":165186},
    {"type":"file","name":"NORMA5.WAV","size":173056},
    {"type":"file","name":"NORMA6.WAV","size":176030},
    {"type":"file","name":"OJANDFBF.WAV","size":296730},
    {"type":"file","name":"ORANGEJUICE.WAV","size":88484},
    {"type":"file","name":"PLAYER1.WAV","size":72868},
    {"type":"file","name":"PLAYER2.WAV","size":81076},
    {"type":"file","name":"PLAYER3.WAV","size":83770},
    {"type":"file","name":"PLAYER4.WAV","size":83016},
    {"type":"file","name":"PLAYERJOIN.WAV","size":98492},
    {"type":"file","name":"PLAYERLEFT.WAV","size":85836},
    {"type":"file","name":"REVIVE.WAV","size":55688},
    {"type":"file","name":"SHINDENKEN.WAV","size":78524},
    {"type":"file","name":"SKIP.WAV","size":75620},
    {"type":"file","name":"START.WAV","size":52340},
    {"type":"file","name":"STOP.WAV","size":48558},
    {"type":"file","name":"TITLE.WAV","size":202912},
    {"type":"file","name":"TRAP.WAV","size":89162},
    {"type":"file","name":"WARPMOVE.WAV","size":77442},
    {"type":"file","name":"WARP.WAV","size":44576},
    {"type":"file","name":"WIN.WAV","size":40624}
  ]}
,
  {"type":"report","directories":1,"files":43}
]
