[
  {"type":"directory","name":"./instance/voice_cha_fernet.pak","size":4096,"contents":[
    {"type":"file","name":"0_0.WAV","size":47154},
    {"type":"file","name":"0_1.WAV","size":58224},
    {"type":"file","name":"0_2.WAV","size":36314},
    {"type":"file","name":"0_3.WAV","size":19570},
    {"type":"file","name":"10_0.WAV","size":171284},
    {"type":"file","name":"10_1.WAV","size":140322},
    {"type":"file","name":"10_2.WAV","size":217290},
    {"type":"file","name":"10_3.WAV","size":128896},
    {"type":"file","name":"1_0.WAV","size":93416},
    {"type":"file","name":"11_0.WAV","size":99356},
    {"type":"file","name":"11_1.WAV","size":92734},
    {"type":"file","name":"11_2.WAV","size":85544},
    {"type":"file","name":"11_3.WAV","size":98124},
    {"type":"file","name":"1_1.WAV","size":76354},
    {"type":"file","name":"12_0.WAV","size":81078},
    {"type":"file","name":"12_1.WAV","size":98514},
    {"type":"file","name":"12_2.WAV","size":68704},
    {"type":"file","name":"12_3.WAV","size":76022},
    {"type":"file","name":"1_2.WAV","size":76796},
    {"type":"file","name":"13_0.WAV","size":108016},
    {"type":"file","name":"13_1.WAV","size":118414},
    {"type":"file","name":"13_2.WAV","size":99864},
    {"type":"file","name":"13_3.WAV","size":145062},
    {"type":"file","name":"1_3.WAV","size":69388},
    {"type":"file","name":"14_0.WAV","size":63286},
    {"type":"file","name":"14_1.WAV","size":88356},
    {"type":"file","name":"14_2.WAV","size":69928},
    {"type":"file","name":"14_3.WAV","size":64272},
    {"type":"file","name":"15_0.WAV","size":43546},
    {"type":"file","name":"15_1.WAV","size":59116},
    {"type":"file","name":"15_2.WAV","size":51738},
    {"type":"file","name":"15_3.WAV","size":87730},
    {"type":"file","name":"16_0.WAV","size":71218},
    {"type":"file","name":"16_1.WAV","size":68532},
    {"type":"file","name":"16_2.WAV","size":84798},
    {"type":"file","name":"16_3.WAV","size":64108},
    {"type":"file","name":"17_0.WAV","size":71946},
    {"type":"file","name":"17_1.WAV","size":78898},
    {"type":"file","name":"17_2.WAV","size":92106},
    {"type":"file","name":"17_3.WAV","size":72858},
    {"type":"file","name":"18_0.WAV","size":60314},
    {"type":"file","name":"18_1.WAV","size":99282},
    {"type":"file","name":"18_2.WAV","size":140526},
    {"type":"file","name":"18_3.WAV","size":97288},
    {"type":"file","name":"19_0.WAV","size":98864},
    {"type":"file","name":"19_1.WAV","size":249654},
    {"type":"file","name":"19_2.WAV","size":117166},
    {"type":"file","name":"19_3.WAV","size":112110},
    {"type":"file","name":"20_0.WAV","size":91314},
    {"type":"file","name":"20_1.WAV","size":212536},
    {"type":"file","name":"20_2.WAV","size":72584},
    {"type":"file","name":"20_3.WAV","size":118306},
    {"type":"file","name":"2_0.WAV","size":76082},
    {"type":"file","name":"21_0.WAV","size":68954},
    {"type":"file","name":"21_1.WAV","size":19476},
    {"type":"file","name":"21_2.WAV","size":52086},
    {"type":"file","name":"21_3.WAV","size":127814},
    {"type":"file","name":"2_1.WAV","size":102034},
    {"type":"file","name":"22_0.WAV","size":99410},
    {"type":"file","name":"22_1.WAV","size":96746},
    {"type":"file","name":"22_2.WAV","size":79952},
    {"type":"file","name":"22_3.WAV","size":96616},
    {"type":"file","name":"2_2.WAV","size":89104},
    {"type":"file","name":"23_0.WAV","size":154602},
    {"type":"file","name":"23_1.WAV","size":231134},
    {"type":"file","name":"23_2.WAV","size":75578},
    {"type":"file","name":"23_3.WAV","size":93810},
    {"type":"file","name":"2_3.WAV","size":120570},
    {"type":"file","name":"24_0.WAV","size":141462},
    {"type":"file","name":"24_1.WAV","size":174710},
    {"type":"file","name":"24_2.WAV","size":155210},
    {"type":"file","name":"24_3.WAV","size":133092},
    {"type":"file","name":"25_0.WAV","size":142262},
    {"type":"file","name":"25_1.WAV","size":157200},
    {"type":"file","name":"25_2.WAV","size":148396},
    {"type":"file","name":"25_3.WAV","size":346804},
    {"type":"file","name":"26_0.WAV","size":78332},
    {"type":"file","name":"26_1.WAV","size":99400},
    {"type":"file","name":"26_2.WAV","size":166056},
    {"type":"file","name":"26_3.WAV","size":157444},
    {"type":"file","name":"27_0.WAV","size":75548},
    {"type":"file","name":"27_1.WAV","size":98168},
    {"type":"file","name":"27_2.WAV","size":120764},
    {"type":"file","name":"27_3.WAV","size":112338},
    {"type":"file","name":"28_0.WAV","size":119692},
    {"type":"file","name":"28_1.WAV","size":154240},
    {"type":"file","name":"28_2.WAV","size":123864},
    {"type":"file","name":"28_3.WAV","size":249932},
    {"type":"file","name":"29_0.WAV","size":85394},
    {"type":"file","name":"29_1.WAV","size":114918},
    {"type":"file","name":"29_2.WAV","size":110288},
    {"type":"file","name":"29_3.WAV","size":62834},
    {"type":"file","name":"3_0.WAV","size":99076},
    {"type":"file","name":"31_0.WAV","size":66478},
    {"type":"file","name":"3_1.WAV","size":72516},
    {"type":"file","name":"32_0.WAV","size":50462},
    {"type":"file","name":"3_2.WAV","size":65076},
    {"type":"file","name":"33_0.WAV","size":17048},
    {"type":"file","name":"3_3.WAV","size":92688},
    {"type":"file","name":"34_0.WAV","size":39580},
    {"type":"file","name":"35_0.WAV","size":220680},
    {"type":"file","name":"36_0.WAV","size":39954},
    {"type":"file","name":"37_0.WAV","size":80824},
    {"type":"file","name":"38_0.WAV","size":64640},
    {"type":"file","name":"39_0.WAV","size":66332},
    {"type":"file","name":"40_0.WAV","size":81078},
    {"type":"file","name":"4_0.WAV","size":184326},
    {"type":"file","name":"41_0.WAV","size":70500},
    {"type":"file","name":"4_1.WAV","size":184326},
    {"type":"file","name":"42_0.WAV","size":84492},
    {"type":"file","name":"43_0.WAV","size":67986},
    {"type":"file","name":"44_0.WAV","size":96550},
    {"type":"file","name":"45_0.WAV","size":22182},
    {"type":"file","name":"46_0.WAV","size":97832},
    {"type":"file","name":"46_1.WAV","size":119810},
    {"type":"file","name":"46_2.WAV","size":102704},
    {"type":"file","name":"46_3.WAV","size":127096},
    {"type":"file","name":"48_0.WAV","size":222944},
    {"type":"file","name":"50_0.WAV","size":159656},
    {"type":"file","name":"5_0.WAV","size":138562},
    {"type":"file","name":"51_0.WAV","size":160256},
    {"type":"file","name":"5_1.WAV","size":94080},
    {"type":"file","name":"52_0.WAV","size":119522},
    {"type":"file","name":"5_2.WAV","size":72592},
    {"type":"file","name":"53_0.WAV","size":213424},
    {"type":"file","name":"5_3.WAV","size":118086},
    {"type":"file","name":"54_0.WAV","size":287090},
    {"type":"file","name":"55_0.WAV","size":166076},
    {"type":"file","name":"56_0.WAV","size":235600},
    {"type":"file","name":"57_0.WAV","size":292716},
    {"type":"file","name":"58_0.WAV","size":44510},
    {"type":"file","name":"59_0.WAV","size":111354},
    {"type":"file","name":"60_0.WAV","size":107510},
    {"type":"file","name":"6_0.WAV","size":108540},
    {"type":"file","name":"61_0.WAV","size":228310},
    {"type":"file","name":"6_1.WAV","size":108308},
    {"type":"file","name":"62_0.WAV","size":120884},
    {"type":"file","name":"6_2.WAV","size":74134},
    {"type":"file","name":"63_0.WAV","size":254404},
    {"type":"file","name":"6_3.WAV","size":94874},
    {"type":"file","name":"64_0.WAV","size":188696},
    {"type":"file","name":"65_0.WAV","size":148654},
    {"type":"file","name":"66_0.WAV","size":177578},
    {"type":"file","name":"67_0.WAV","size":116572},
    {"type":"file","name":"68_0.WAV","size":155194},
    {"type":"file","name":"69_0.WAV","size":135852},
    {"type":"file","name":"70_0.WAV","size":312902},
    {"type":"file","name":"7_0.WAV","size":70728},
    {"type":"file","name":"71_0.WAV","size":411874},
    {"type":"file","name":"7_1.WAV","size":90522},
    {"type":"file","name":"72_0.WAV","size":228790},
    {"type":"file","name":"7_2.WAV","size":73504},
    {"type":"file","name":"73_0.WAV","size":91962},
    {"type":"file","name":"7_3.WAV","size":95610},
    {"type":"file","name":"8_0.WAV","size":52322},
    {"type":"file","name":"8_1.WAV","size":67942},
    {"type":"file","name":"8_2.WAV","size":87912},
    {"type":"file","name":"8_3.WAV","size":46726},
    {"type":"file","name":"9_0.WAV","size":86724},
    {"type":"file","name":"9_1.WAV","size":101794},
    {"type":"file","name":"9_2.WAV","size":43660},
    {"type":"file","name":"9_3.WAV","size":90910}
  ]}
,
  {"type":"report","directories":1,"files":162}
]
