[
  {"type":"directory","name":"data/define/ko","size":12288,"contents":[
    {"type":"file","name":"abilities.txt","size":1048,"md5":"f955a08b112eccd136c012f4cc2712b9"},
    {"type":"file","name":"arcade_rules.txt","size":1101,"md5":"0e7493449a97b75b3d28c9f817660d0b"},
    {"type":"file","name":"arcade.txt","size":1834,"md5":"7a6f9fb5498cbb539656338d73505f76"},
    {"type":"file","name":"bountyhunt_inventory.txt","size":5917,"md5":"8fc5d4b98d5d620daeaaa63ace00369f"},
    {"type":"file","name":"bountyshop_items.txt","size":7307,"md5":"ab939314f712e70c998f1f3746e442f5"},
    {"type":"file","name":"campaign_10yearanniversary.txt","size":1930,"md5":"cbe3141fcebf5108a8c0ed470a6d26b6"},
    {"type":"file","name":"campaign_chaos.txt","size":373,"md5":"06e3ab3b5a671ce5750a05963391d62c"},
    {"type":"file","name":"campaign_chnewyear2019.txt","size":3221,"md5":"0bd005113faee87ae82bf4c4dfa31ea8"},
    {"type":"file","name":"campaign_christmas2018.txt","size":4908,"md5":"4500624aa3748a64aadf840f59b7860a"},
    {"type":"file","name":"campaign_christmas.txt","size":4794,"md5":"c0777a7645de1f12c6bec69aefcb0fd0"},
    {"type":"file","name":"campaign_ellielulu.txt","size":11580,"md5":"2349e6c3e67f623e316c106ecede648a"},
    {"type":"file","name":"campaign_extra.txt","size":1092,"md5":"46faabdb7159cee5d2d17f85fecdd09f"},
    {"type":"file","name":"campaign_fall2020.txt","size":7679,"md5":"06a71a0927babfbe523b320e7c129cf2"},
    {"type":"file","name":"campaign_halloween2018.txt","size":6173,"md5":"3c419e4e4afb1e1a70f6f728b9d6734e"},
    {"type":"file","name":"campaign_halloween2019.txt","size":5441,"md5":"1c3d35de34ffc6b21092798d75239d42"},
    {"type":"file","name":"campaign_hw2021.txt","size":5636,"md5":"90142a0065ffa88d38fdcd4121c84735"},
    {"type":"file","name":"campaign_kai.txt","size":11709,"md5":"a3b2f32014a8f26fd901886e87c3bb10"},
    {"type":"file","name":"campaign_marc.txt","size":10547,"md5":"0568d09ec95a35f6706508ad93e02b53"},
    {"type":"file","name":"campaign_mio_interlude.txt","size":313,"md5":"53464f5e703a24c743ad2468b523c0e6"},
    {"type":"file","name":"campaign_mio.txt","size":6278,"md5":"6e710c4e8423e2613480c7411ffc0926"},
    {"type":"file","name":"campaign_miuceore.txt","size":12393,"md5":"fa5138652e3a2fc64b735d16948c69ae"},
    {"type":"file","name":"campaign_nicoarthur.txt","size":10469,"md5":"f168bc372a749a7c7eea5060d9ce9720"},
    {"type":"file","name":"campaign_oldguardian.txt","size":12210,"md5":"05571c77609e6e41f992436619cb29ed"},
    {"type":"file","name":"campaign_other.txt","size":1730,"md5":"dbf4bb6f30762d0a18b893f275a7d59c"},
    {"type":"file","name":"campaign_qp.txt","size":11409,"md5":"d0e37fb942a260c3116f3964bacfe610"},
    {"type":"file","name":"campaign_roneteo.txt","size":3190,"md5":"898c7a02e24c9f2995bb1ffa26452d17"},
    {"type":"file","name":"campaign_s3_summer2024.txt","size":7165,"md5":"77849c624fce3716e74c0d91e6b0ab1d"},
    {"type":"file","name":"campaign_secretsanta.txt","size":4107,"md5":"d610b87338b01b5405cc5c430c835971"},
    {"type":"file","name":"campaign_spring2018.txt","size":9691,"md5":"f31ded89051116eec6a83437a68bc115"},
    {"type":"file","name":"campaign_spring2019.txt","size":2252,"md5":"4148a5be300334e838ff186d05749502"},
    {"type":"file","name":"campaign_spring2020.txt","size":3982,"md5":"f1e7ce4f693b68b03a75183554b86e4c"},
    {"type":"file","name":"campaign_starbreaker.txt","size":11760,"md5":"1a3a9b5e8a793f9c6ae28522f65cff1d"},
    {"type":"file","name":"campaign_suguri.txt","size":11086,"md5":"f4d47e9ad8f13701bd1ed225e4876cc0"},
    {"type":"file","name":"campaign_summer2018.txt","size":4549,"md5":"2f646de164bfc47457634cc541f0847a"},
    {"type":"file","name":"campaign_summer2019.txt","size":3570,"md5":"54e358100481e1c896a90581bea7e7e5"},
    {"type":"file","name":"campaign_summer2020.txt","size":5007,"md5":"58ee24d5e28166995fcca2354fefe39c"},
    {"type":"file","name":"campaign_summer2021.txt","size":4956,"md5":"a791b7f7c3df1c474fe9f2f7fa14265f"},
    {"type":"file","name":"campaign_summer2022.txt","size":6177,"md5":"73172e0a8f462fb0e8c7dc12a27b58dc"},
    {"type":"file","name":"campaign_summer2023.txt","size":6071,"md5":"1d70a8420ceb2d1a821631f781695db2"},
    {"type":"file","name":"campaign_sweetbreaker.txt","size":10545,"md5":"9d4b80337619bda9008c9012cbd9b5ba"},
    {"type":"file","name":"campaign.txt","size":4907,"md5":"0e209540179b25575b8be218f888844d"},
    {"type":"file","name":"campaign_valentine2018.txt","size":6574,"md5":"cfefebd75cc65c0641f081aa152c0fe4"},
    {"type":"file","name":"campaign_warudaprisonbreak.txt","size":18663,"md5":"9c0b5cd04c363e2e35aaae1d4042a4ff"},
    {"type":"file","name":"campaign_winter2020.txt","size":7695,"md5":"ea6703b5b9bf82b0ee5948f4801ca9b0"},
    {"type":"file","name":"campaign_winter2022.txt","size":4966,"md5":"50076e596320c2e4be77fcfdd9d23736"},
    {"type":"file","name":"campaign_winter2023.txt","size":12047,"md5":"1f36a385dfe9ef21a71517a38c8d69ce"},
    {"type":"file","name":"cardartists.txt","size":2049,"md5":"207de767b2d11b43de75134d3dfb62ad"},
    {"type":"file","name":"cards_2.txt","size":51454,"md5":"2396e326984f9304e0640b6f13f60c55"},
    {"type":"file","name":"cards_bounty.txt","size":9982,"md5":"d20556d8d44b886b6ae7dcc430cbfc81"},
    {"type":"file","name":"cards_coop.txt","size":56482,"md5":"aa4444129a30654f62cb9f2ed604c5a4"},
    {"type":"file","name":"cards_effect_coop.txt","size":10427,"md5":"588115a2eb95a5bdea31d3494462992e"},
    {"type":"file","name":"cards_effect.txt","size":24911,"md5":"adc36b140ee481766993c64cf4c96726"},
    {"type":"file","name":"cards_misc.txt","size":390,"md5":"1e73c1626a6d5af089114a0773bd820b"},
    {"type":"file","name":"cards_mushroom.txt","size":3125,"md5":"e89008fafd4e4185744789ecef7fe9da"},
    {"type":"file","name":"cards.txt","size":12396,"md5":"be7b6d9f6b9b6e557822a13de46cc080"},
    {"type":"file","name":"challenges.txt","size":2879,"md5":"7fa3adbcebf54dd0b2156b87e5e2982c"},
    {"type":"file","name":"chaos_mutators.txt","size":4959,"md5":"76e6b7ad1906bc0cda2851fc76314e68"},
    {"type":"file","name":"characterselect.txt","size":749,"md5":"8fc9a626e7c06bc59fdaaff4bdec8608"},
    {"type":"file","name":"charavoice_alicianrone.txt","size":5161,"md5":"8025db1023a59be1a42c634ed974231c"},
    {"type":"file","name":"charavoice_alte.txt","size":4896,"md5":"eca2983edd05d99712dc445311968a54"},
    {"type":"file","name":"charavoice_arnelle.txt","size":5315,"md5":"48414312736ceeffb35cf8de256e986f"},
    {"type":"file","name":"charavoice_arthur.txt","size":4667,"md5":"8b1aff11503dc085f6fb6ffc841df86d"},
    {"type":"file","name":"charavoice_aru.txt","size":4520,"md5":"7906fef92f7ffab01545273ebf1086e9"},
    {"type":"file","name":"charavoice_bourbon.txt","size":5674,"md5":"ad15550affd17a22731151c13734972c"},
    {"type":"file","name":"charavoice_ceor.txt","size":5652,"md5":"0b19e0246d8a7370dd7242ae6e514a17"},
    {"type":"file","name":"charavoice_chris.txt","size":5838,"md5":"dfed51a09b64908af3640f88c495c7eb"},
    {"type":"file","name":"charavoice_cook.txt","size":4236,"md5":"d6e21d1167f5305cbad4ac64bfe21867"},
    {"type":"file","name":"charavoice_elliehyper.txt","size":5608,"md5":"fb8cc1ce387639d8b10f3b43a9fc74dc"},
    {"type":"file","name":"charavoice_ellie.txt","size":5677,"md5":"3466480ab6598e1776ca2ad57fcae613"},
    {"type":"file","name":"charavoice_fae.txt","size":1849,"md5":"0aefe36cf03a2e6d61c1894b0af43087"},
    {"type":"file","name":"charavoice_fernetnoble.txt","size":6818,"md5":"27d8f45739d3abd83dff72dcae1634ad"},
    {"type":"file","name":"charavoice_fernet.txt","size":4391,"md5":"ff59f44cc02f565fed78023f731a48b2"},
    {"type":"file","name":"charavoice_grain.txt","size":6262,"md5":"bb85a01b9ce5ed03dcd2f31bc37915b5"},
    {"type":"file","name":"charavoice_guardian.txt","size":1767,"md5":"6da80725b86a317382be54a899510925"},
    {"type":"file","name":"charavoice_halena.txt","size":4280,"md5":"2d841892e3565e1610c3630776d61f53"},
    {"type":"file","name":"charavoice_himem.txt","size":4650,"md5":"6f6ddc0ef2c2bff83c462626844342ad"},
    {"type":"file","name":"charavoice_hime.txt","size":5000,"md5":"7de07d047238416dd70ff2edda4ca823"},
    {"type":"file","name":"charavoice_iru.txt","size":4659,"md5":"3bc77edba5bca6c0c1f9006d2e714d11"},
    {"type":"file","name":"charavoice_islay.txt","size":4699,"md5":"47d0ba97a098a2ba0d4d5b99a81376cd"},
    {"type":"file","name":"charavoice_kae.txt","size":4210,"md5":"b0bde860747df5016eb3ada46becbc7f"},
    {"type":"file","name":"charavoice_kaihero.txt","size":5043,"md5":"0b7139e7be26be2ffd112b0d3e3ca4ac"},
    {"type":"file","name":"charavoice_kai.txt","size":4219,"md5":"24f8aaafc8af4da684fd8ced98918f16"},
    {"type":"file","name":"charavoice_kiriko.txt","size":6046,"md5":"ac6333b769f71cf248a24b3b42aa278f"},
    {"type":"file","name":"charavoice_krilap.txt","size":6350,"md5":"a13dca4c7f92222b6dd25cfd284fda44"},
    {"type":"file","name":"charavoice_krila.txt","size":5968,"md5":"63d9acb913198ec0bc37f8032c1b33ec"},
    {"type":"file","name":"charavoice_kyoko.txt","size":5037,"md5":"14f9db06bc6f491360df88478d5d2af4"},
    {"type":"file","name":"charavoice_kyousuke.txt","size":4853,"md5":"3a95f94671d7c56d83e8e7e979f5ee15"},
    {"type":"file","name":"charavoice_kyupita.txt","size":4757,"md5":"93923b11387c1d228f277c011468f5c8"},
    {"type":"file","name":"charavoice_lonerider.txt","size":5992,"md5":"3bf07f4795ef65e71419b53ac4721f7b"},
    {"type":"file","name":"charavoice_luludark.txt","size":4972,"md5":"74cac2bc8c862c7579ed5f06d884f326"},
    {"type":"file","name":"charavoice_lulu.txt","size":5155,"md5":"817762d99b05691aec26ab5e14a935e8"},
    {"type":"file","name":"charavoice_malt.txt","size":6344,"md5":"2246a7f410553f8d504c719e7d5d3ab1"},
    {"type":"file","name":"charavoice_marc.txt","size":3608,"md5":"49f82fcc56c71fe14dc9edee6d5cdebf"},
    {"type":"file","name":"charavoice_maynie.txt","size":6054,"md5":"f892296547597b0c1e0b125900a88be1"},
    {"type":"file","name":"charavoice_mei.txt","size":4760,"md5":"2230b657dc63bd8ef09567a25571c79e"},
    {"type":"file","name":"charavoice_merchant.txt","size":7118,"md5":"9bff1b52452d22729c4e8fe257bfdc22"},
    {"type":"file","name":"charavoice_mescal.txt","size":5709,"md5":"2c9f3ed4fd0842d4425f7ab1f35e6718"},
    {"type":"file","name":"charavoice_mimyuuj.txt","size":5028,"md5":"662732ebc6308417b391de4ecd0f287a"},
    {"type":"file","name":"charavoice_mimyuu.txt","size":6177,"md5":"df804816c76a8174408492c39cce850c"},
    {"type":"file","name":"charavoice_miof.txt","size":5465,"md5":"f7e9a282d72a411e0a6c7967a6345ca7"},
    {"type":"file","name":"charavoice_mio.txt","size":5221,"md5":"1a88735b98e9b95a03260bd763fc31a4"},
    {"type":"file","name":"charavoice_mira.txt","size":5146,"md5":"0130817b3a400db915c92beff65fb0a1"},
    {"type":"file","name":"charavoice_miusaki.txt","size":4602,"md5":"9270d7e19968572b363378df5160d73e"},
    {"type":"file","name":"charavoice_mpoppo.txt","size":877,"md5":"2481093ae6924ab1b95badcf44f1ac13"},
    {"type":"file","name":"charavoice_nanako.txt","size":4973,"md5":"3b69330ba7e9d0fda8ed9d2502ca3282"},
    {"type":"file","name":"charavoice_nath.txt","size":5521,"md5":"f92f95acaaede96b39d3b64be86d3fc5"},
    {"type":"file","name":"charavoice_natsumi.txt","size":4577,"md5":"8b4b844ad0d4da85e0f1383dc73aace5"},
    {"type":"file","name":"charavoice_nico.txt","size":5759,"md5":"456a747c9df2b28fe4cd776124d1758b"},
    {"type":"file","name":"charavoice_noname.txt","size":5572,"md5":"8e38ae50a004cbf9b459bcfa7a0a886e"},
    {"type":"file","name":"charavoice_peat.txt","size":4596,"md5":"07a5fb885ba4b15a37abbe8274dd26b8"},
    {"type":"file","name":"charavoice_pomeranius.txt","size":4856,"md5":"44822af7d3c0ac81227929566806c045"},
    {"type":"file","name":"charavoice_poppomama.txt","size":6247,"md5":"8129d1cae41c08e56a1aef7e1bf35d0a"},
    {"type":"file","name":"charavoice_poppo.txt","size":3794,"md5":"394b952414f9c0a4a193feefff79157b"},
    {"type":"file","name":"charavoice_qp.txt","size":4661,"md5":"20e3b47da5aa7452213f4a2fe835ea68"},
    {"type":"file","name":"charavoice_reika.txt","size":4515,"md5":"18739f32b3c68ab12590d465a18c2493"},
    {"type":"file","name":"charavoice_rogue.txt","size":1926,"md5":"14647d158674a00674d86a5fb72f7ff3"},
    {"type":"file","name":"charavoice_saki.txt","size":5270,"md5":"45093604e0edbfeff315acb248fed135"},
    {"type":"file","name":"charavoice_sham_idol.txt","size":3924,"md5":"3d5bad638b8b3aa6aa8e23897fca1b08"},
    {"type":"file","name":"charavoice_sham.txt","size":4512,"md5":"b02c0e02296be96b6a135f1a54c39c58"},
    {"type":"file","name":"charavoice_sherry.txt","size":4362,"md5":"8c05b1eef00eb729879778816f72bfed"},
    {"type":"file","name":"charavoice_shifu.txt","size":4384,"md5":"8f0a14dd4fea907662f3ada69109452a"},
    {"type":"file","name":"charavoice_sora_idol.txt","size":3613,"md5":"43caa8349d47f471bad4f59798513cc0"},
    {"type":"file","name":"charavoice_sora.txt","size":4307,"md5":"ba5bdc8fc1beefd065d102cbbf7238fa"},
    {"type":"file","name":"charavoice_starb.txt","size":4930,"md5":"58ff6bde930784bd48bc267a187b406f"},
    {"type":"file","name":"charavoice_suguri46.txt","size":5111,"md5":"64180d65f1d19975b12244faceb2b9d3"},
    {"type":"file","name":"charavoice_suguri.txt","size":3742,"md5":"9addbdb40b9fc14b8c9b3b062696c5a7"},
    {"type":"file","name":"charavoice_sumika.txt","size":6388,"md5":"c44ab0b8e051677e8ad32bfeeff4f0c8"},
    {"type":"file","name":"charavoice_sweetblogger.txt","size":5146,"md5":"2a9b88a25e81663021966eca13cf895d"},
    {"type":"file","name":"charavoice_sweetb.txt","size":5366,"md5":"f69a1d82a5ee42e415791c98bdb80f6d"},
    {"type":"file","name":"charavoice_sweetcreator.txt","size":5889,"md5":"aa7f242d553a97d4571644f1c2e97b38"},
    {"type":"file","name":"charavoice_sweetmaker.txt","size":6099,"md5":"209d53ed7bfbf9aa643fb00eae7400c8"},
    {"type":"file","name":"charavoice_syura.txt","size":5133,"md5":"bd28a23f4963ee75658d39ef4cb38651"},
    {"type":"file","name":"charavoice_teotoratta.txt","size":5890,"md5":"7b9e9633477ee1bf67c75bb8cf48bc93"},
    {"type":"file","name":"charavoice_teq_minion.txt","size":768,"md5":"8b7e1b955f558ef4d7d75ca80f993eb4"},
    {"type":"file","name":"charavoice_tequila.txt","size":5164,"md5":"3ec6c7c276a00cdc62c2f14f409d31bd"},
    {"type":"file","name":"charavoice_tomato.txt","size":8534,"md5":"a6d12374b5af4711d65fa5789d62c889"},
    {"type":"file","name":"charavoice_tomomoc.txt","size":4269,"md5":"5a88959652409ac8ba00b38297c074ec"},
    {"type":"file","name":"charavoice_tomomose.txt","size":3537,"md5":"f45a86e648c5976e2df91fc1a05453b3"},
    {"type":"file","name":"charavoice_tomomo.txt","size":5249,"md5":"a7524119e75e7c3ec39540ef1bc47fbe"},
    {"type":"file","name":"charavoice_tsih.txt","size":5374,"md5":"023dfadb338385e30652868a94da4b1e"},
    {"type":"file","name":"charavoice_watty.txt","size":4852,"md5":"0ad85da8507b6dcac12583f99c3c35d5"},
    {"type":"file","name":"charavoice_yukid.txt","size":4670,"md5":"64c9a838b9832255333d3f15a5d7d5ef"},
    {"type":"file","name":"charavoice_yuki.txt","size":4882,"md5":"813dbc9d165ff385f9be62e6c6c720a9"},
    {"type":"file","name":"charavoice_yuuki_angel.txt","size":3797,"md5":"e97072b32b451122546a8d3589235c51"},
    {"type":"file","name":"charavoice_yuuki_devil.txt","size":3795,"md5":"aed1144a6b60ca5f360697c2ed00a12a"},
    {"type":"file","name":"charavoice_yuuki.txt","size":7039,"md5":"baa2a702d81e5815bce5638747706caf"},
    {"type":"file","name":"codex.txt","size":32968,"md5":"8b4a21b84d4fd935d911aa36cce42a5f"},
    {"type":"file","name":"comment.txt","size":7468,"md5":"c6b0a581ae2ca4100467e27b926490e7"},
    {"type":"file","name":"config.txt","size":4233,"md5":"9e58458be1c5b284c71892f07fdabef3"},
    {"type":"file","name":"consumables.txt","size":824,"md5":"5786ed205b57d0946d751ed45680653b"},
    {"type":"file","name":"discord.txt","size":1120,"md5":"65a9b74d5af4b09a02ef0f29aa222e4e"},
    {"type":"file","name":"error.txt","size":184,"md5":"9efa93a9e06bca2a7618e83a1acc135c"},
    {"type":"file","name":"eventnames.txt","size":580,"md5":"2445617e0d5338536d59aa5e9a248694"},
    {"type":"file","name":"fieldevents.txt","size":3625,"md5":"0cb8f0493fca28c9892022da2e10a1a1"},
    {"type":"file","name":"fieldnames.txt","size":3445,"md5":"81d18fddc034185f87dbcfbf9fb9e631"},
    {"type":"file","name":"game_message.txt","size":4322,"md5":"45ddad5de69379b04c81a264b750e6d9"},
    {"type":"file","name":"game_norma.txt","size":1286,"md5":"9e085ce89cf260c9144054d68a2ea0bd"},
    {"type":"file","name":"game_system.txt","size":3417,"md5":"5ee338d06b0f91e1976d2f6c78574ea0"},
    {"type":"file","name":"game_tutorial.txt","size":5473,"md5":"61de41c34c52fe3c45ca951c3345a9b4"},
    {"type":"file","name":"launcher.txt","size":903,"md5":"976fec9170a69ba1a75676aab9cac063"},
    {"type":"file","name":"menuscreens.txt","size":53727,"md5":"b1975f43713664d63026f3ade989c734"},
    {"type":"file","name":"mixers.txt","size":3102,"md5":"12b830e6bdeb2352c82511c559527015"},
    {"type":"file","name":"multiplayer.txt","size":5655,"md5":"7e2244a16426a4903cdad3da55ad3555"},
    {"type":"file","name":"pets.txt","size":6015,"md5":"06bed60dbd5c6d084aad605e605926e4"},
    {"type":"file","name":"pins.txt","size":9408,"md5":"f177daf2d0385cf902f4ef3222e7d2fd"},
    {"type":"file","name":"profile.txt","size":9721,"md5":"3bc6b9866a3507f257e9e479d93f4c2e"},
    {"type":"file","name":"result.txt","size":805,"md5":"a8682cc1a9ad68eabbcf300b358f5789"},
    {"type":"file","name":"shop.txt","size":5154,"md5":"fad69fc695c1d1ad8fec1de0696dee0f"},
    {"type":"file","name":"unitgames.txt","size":787,"md5":"8b6b5d5dd689a15e48bf8b59bf50e11d"},
    {"type":"file","name":"units.txt","size":25230,"md5":"b4e376a6f35fae0a2cc1e4b1eced69e9"},
    {"type":"file","name":"voiceactors.txt","size":2811,"md5":"3a458b56e47523fb5c11bb8136971f19"}
  ]}
,
  {"type":"report","directories":1,"files":171}
]
